chucknorrisfacts/__init__.py
chucknorrisfacts/chucknorrisfacts.py
chucknorrisfacts/cli.py
chucknorrisfacts-0.2.7.dist-info/DESCRIPTION.rst
chucknorrisfacts-0.2.7.dist-info/METADATA
chucknorrisfacts-0.2.7.dist-info/RECORD
chucknorrisfacts-0.2.7.dist-info/WHEEL
chucknorrisfacts-0.2.7.dist-info/entry_points.txt
chucknorrisfacts-0.2.7.dist-info/metadata.json
chucknorrisfacts-0.2.7.dist-info/top_level.txt
