Metadata-Version: 2.0
Name: chucknorrisfacts
Version: 0.2.7
Summary: Display a random Chuck Norris Joke
Home-page: https://github.com/JoseRZapata/chucknorrisfacts
Author: Jose R. Zapata
Author-email: jjrzg@hotmail.com
License: MIT license
Keywords: chuck,norris,jokes
Platform: UNKNOWN
Classifier: Development Status :: 2 - Pre-Alpha
Classifier: Intended Audience :: Developers
Classifier: License :: OSI Approved :: MIT License
Classifier: Natural Language :: English
Classifier: Programming Language :: Python :: 3
Classifier: Programming Language :: Python :: 3.4
Classifier: Programming Language :: Python :: 3.5
Classifier: Programming Language :: Python :: 3.6
Requires-Dist: Click (>=6.0)
Requires-Dist: requests (>=2.18)
